_richdem.cpython-35m-x86_64-linux-gnu.so
richdem/cli.py
richdem/__init__.py
richdem-0.3.4.dist-info/WHEEL
richdem-0.3.4.dist-info/top_level.txt
richdem-0.3.4.dist-info/METADATA
richdem-0.3.4.dist-info/RECORD
richdem-0.3.4.dist-info/entry_points.txt
