Metadata-Version: 2.1
Name: richdem
Version: 0.3.4
Summary: High-Performance Terrain Analysis
Home-page: https://github.com/r-barnes/richdem
Author: Richard Barnes
Author-email: rbarnes@umn.edu
License: GPLv3
Keywords: GIS terrain hydrology geomorphology raster
Platform: UNKNOWN
Classifier: Development Status :: 4 - Beta
Classifier: Environment :: Console
Classifier: Intended Audience :: Developers
Classifier: Intended Audience :: End Users/Desktop
Classifier: Intended Audience :: Education
Classifier: Intended Audience :: Science/Research
Classifier: Intended Audience :: Other Audience
Classifier: License :: OSI Approved :: GNU General Public License v3 (GPLv3)
Classifier: Natural Language :: English
Classifier: Topic :: Scientific/Engineering :: GIS
Classifier: Topic :: Scientific/Engineering :: Information Analysis
Classifier: Topic :: Scientific/Engineering :: Visualization
Classifier: Topic :: Software Development :: Libraries
Classifier: Programming Language :: Python :: 2
Classifier: Programming Language :: Python :: 2.6
Classifier: Programming Language :: Python :: 2.7
Classifier: Programming Language :: Python :: 3
Classifier: Programming Language :: Python :: 3.2
Classifier: Programming Language :: Python :: 3.3
Classifier: Programming Language :: Python :: 3.4
Requires-Dist: numpy (<1.12,>=1.7); python_version < "3.4" and python_version > "3.0"
Requires-Dist: numpy (<2,>=1.7); python_version > "3.4" or python_version < "3.0"
